CY3761/__init__.py
CY3761/build/res.py
CY3761/build/string.py
CY3761/build/template/res/init.py
CY3761/build/template/res/t_config.js
CY3761/build/template/res/t_main.js
CY3761/build/template/res/t_main.py
CY3761/build/template/res/t_setup.py
CY3761/js/helper.py
CY3761/js/npm.py
CY3761/js/0/helper.js
CY3761/js/0/test.js
CY3761/js/1/curlconverter.js
CY3761/js/1/helper.js
CY3761/js/1/package.json
CY3761/py/helper.py
CY3761/send/config.py
CY3761/send/req.py
CY3761/send/res.py
CY3761/storage/open.py
CY3761/string/ascii.py
CY3761/string/config.py
CY3761/string/helper.py
cy3761-2024.11206.10922.dist-info/METADATA
cy3761-2024.11206.10922.dist-info/WHEEL
cy3761-2024.11206.10922.dist-info/RECORD
