Metadata-Version: 2.3
Name: CY3761
Version: 2024.11206.10922
Author-email: CY3761 <fb764bc@outlook.com>
License: MIT License
Classifier: License :: OSI Approved :: MIT License
Classifier: Operating System :: OS Independent
Classifier: Programming Language :: Python :: 3
Requires-Python: >=3.11.10
Requires-Dist: fake-useragent
Requires-Dist: pyexecjs2
Requires-Dist: requests
